{"data": [[["0.0511"], ["298.15"], ["101"], ["865.8", "3.6"]], [["0.1525"], ["298.15"], ["101"], ["975.9", "1.9"]], [["0.2378"], ["298.15"], ["101"], ["1041.9", "2.1"]], [["0.3537"], ["298.15"], ["101"], ["1126.3", "3.4"]], [["0.4417"], ["298.15"], ["101"], ["1172.9", "4.1"]], [["0.5013"], ["298.15"], ["101"], ["1192", "20"]], [["0.5427"], ["298.15"], ["101"], ["1214.9", "4.8"]], [["0.6463"], ["298.15"], ["101"], ["1249.3", "5.4"]], [["0.7423"], ["298.15"], ["101"], ["1278.2", "5.9"]], [["0.8454"], ["298.15"], ["101"], ["1303.2", "6.3"]], [["0.9551"], ["298.15"], ["101"], ["1325.6", "6.7"]]], "dhead": [["Mole fraction of 1,3-dimethylimidazolium methylsulfate", "Liquid"], ["Temperature, K", null], ["Pressure, kPa", null], ["Specific density, kg/m<SUP>3</SUP>", "Liquid"]], "components": [{"name": "ethanol", "mw": "46.07", "idout": "AAIshn", "sample": [["Source:", "commercial source"], ["Initial purification:", "stated by supplier"], ["Initial purity:", "99.9 mass %"], ["Final purification:", "gas chromatography;Karl Fischer titration"], ["Final purity:", "99.8 mass %;0.02 water mass %(dried with chemical reagent;fractional distillation)"]], "formula": "C<SUB>2</SUB>H<SUB>6</SUB>O"}, {"name": "1,3-dimethylimidazolium methylsulfate", "mw": "208.23", "idout": "AAoCiZ", "sample": [["Source:", "commercial source"], ["Purification:", "stated by supplier"], ["Purity:", "98 mass %"], ["Purity analysis:", "dried by vacuum heating"]], "formula": "C<SUB>6</SUB>H<SUB>12</SUB>N<SUB>2</SUB>O<SUB>4</SUB>S"}], "ref": {"full": "Domanska, U.; Pobudkowska, A.; Wisniewska, A. (2006) J. Solution Chem. 35(3), 311-334.", "title": "Solubility and Excess Molar Properties of 1,3-Dimethylimidazolium Methylsulfate, or 1-Butyl-3-Methylimidazolium Methylsulfate, or 1-Butyl-3-Methylimidazolium Octylsulfate Ionic Liquids with n-Alkanes and Alcohols: Analysis in Terms of the PFP and FBT Models"}, "constr": [], "phases": ["Liquid"], "footer": "", "expmeth": "Vibrating tube method", "title": "Volumetric properties: Specific density", "solvent": null}